hsvfinder/__init__.py
hsvfinder/__main__.py
hsvfinder-0.0.2.dist-info/LICENSE.txt
hsvfinder-0.0.2.dist-info/METADATA
hsvfinder-0.0.2.dist-info/WHEEL
hsvfinder-0.0.2.dist-info/top_level.txt
hsvfinder-0.0.2.dist-info/RECORD
